fastsqlite3/__init__.py
fastsqlite3/py.typed
fastsqlite3-2.0.0a0.dist-info/LICENSE
fastsqlite3-2.0.0a0.dist-info/METADATA
fastsqlite3-2.0.0a0.dist-info/WHEEL
fastsqlite3-2.0.0a0.dist-info/top_level.txt
fastsqlite3-2.0.0a0.dist-info/RECORD
